maki_proxy.py
makiproxy5-0.0.1.dist-info/LICENSE.txt
makiproxy5-0.0.1.dist-info/METADATA
makiproxy5-0.0.1.dist-info/WHEEL
makiproxy5-0.0.1.dist-info/top_level.txt
makiproxy5-0.0.1.dist-info/RECORD
