Metadata-Version: 2.1
Name: makiproxy5
Version: 0.0.1
Summary: A socks 5 proxy server written in Python, class based.
Home-page: https://github.com/makiisthenes/Proxy5Server
Author: Michael Peres
Author-email: michaelperes1@gmail.com
License: UNKNOWN
Platform: UNKNOWN
Classifier: Programming Language :: Python :: 3
Classifier: Programming Language :: Python :: 3.6
Classifier: Programming Language :: Python :: 3.7
Classifier: License :: OSI Approved :: GNU General Public License v2 or later (GPLv2+)
Classifier: Operating System :: OS Independent
Classifier: Natural Language :: English
Classifier: Topic :: Internet
Classifier: Topic :: Internet :: Proxy Servers
Requires-Dist: certifi (==2022.6.15)
Requires-Dist: idna (==3.3)
Requires-Dist: netifaces (==0.11.0)
Requires-Dist: requests (==2.28.1)
Requires-Dist: urllib3 (==1.26.10)
